odoo9_addon_barcodes_generator_product-9.0.1.0.0.99.dev4-py2.7-nspkg.pth
odoo9_addon_barcodes_generator_product-9.0.1.0.0.99.dev4.dist-info/DESCRIPTION.rst
odoo9_addon_barcodes_generator_product-9.0.1.0.0.99.dev4.dist-info/METADATA
odoo9_addon_barcodes_generator_product-9.0.1.0.0.99.dev4.dist-info/RECORD
odoo9_addon_barcodes_generator_product-9.0.1.0.0.99.dev4.dist-info/WHEEL
odoo9_addon_barcodes_generator_product-9.0.1.0.0.99.dev4.dist-info/metadata.json
odoo9_addon_barcodes_generator_product-9.0.1.0.0.99.dev4.dist-info/namespace_packages.txt
odoo9_addon_barcodes_generator_product-9.0.1.0.0.99.dev4.dist-info/top_level.txt
odoo_addons/barcodes_generator_product/README.rst
odoo_addons/barcodes_generator_product/__init__.py
odoo_addons/barcodes_generator_product/__openerp__.py
odoo_addons/barcodes_generator_product/demo/barcode_rule.xml
odoo_addons/barcodes_generator_product/demo/function.xml
odoo_addons/barcodes_generator_product/demo/product.xml
odoo_addons/barcodes_generator_product/demo/res_users.xml
odoo_addons/barcodes_generator_product/i18n/barcodes_generator_product.pot
odoo_addons/barcodes_generator_product/i18n/fr.po
odoo_addons/barcodes_generator_product/migrations/9.0.1.0.0/post-migration.py
odoo_addons/barcodes_generator_product/models/__init__.py
odoo_addons/barcodes_generator_product/models/barcode_rule.py
odoo_addons/barcodes_generator_product/models/product_product.py
odoo_addons/barcodes_generator_product/models/product_template.py
odoo_addons/barcodes_generator_product/static/description/icon.png
odoo_addons/barcodes_generator_product/static/description/product_template_manual_generation.png
odoo_addons/barcodes_generator_product/tests/__init__.py
odoo_addons/barcodes_generator_product/tests/test_barcodes_generator_product.py
odoo_addons/barcodes_generator_product/views/view_product_product.xml
odoo_addons/barcodes_generator_product/views/view_product_template.xml
